MANIFEST.in
README.rst
setup.py
django_exportdb.egg-info/PKG-INFO
django_exportdb.egg-info/SOURCES.txt
django_exportdb.egg-info/dependency_links.txt
django_exportdb.egg-info/not-zip-safe
django_exportdb.egg-info/requires.txt
django_exportdb.egg-info/top_level.txt
exportdb/__init__.py
exportdb/apps.py
exportdb/compat.py
exportdb/conf.py
exportdb/exporter.py
exportdb/models.py
exportdb/permissions.py
exportdb/tasks.py
exportdb/urls.py
exportdb/views.py
exportdb/admin/__init__.py
exportdb/management/__init__.py
exportdb/management/commands/__init__.py
exportdb/management/commands/exportdb.py
exportdb/templates/exportdb/base.html
exportdb/templates/exportdb/confirm.html
exportdb/templates/exportdb/in_progress.html