Metadata-Version: 1.1
Name: django-exportdb
Version: 0.4.7
Summary: Dump the entire database to xlsx workbook with a sheet per model
Home-page: https://github.com/maykinmedia/django-exportdb
Author: Maykin Media, Sergei Maertens
Author-email: sergei@maykinmedia.nl
License: MIT
Platform: any
Classifier: Development Status :: 3 - Alpha
Classifier: Framework :: Django :: 1.6
Classifier: Framework :: Django :: 1.7
Classifier: Framework :: Django :: 1.8
Classifier: Intended Audience :: Developers
Classifier: Operating System :: Unix
Classifier: Operating System :: MacOS
Classifier: Operating System :: Microsoft :: Windows
Classifier: Programming Language :: Python :: 2.7
Classifier: Programming Language :: Python :: 3.4
Classifier: Topic :: Software Development :: Libraries :: Application Frameworks
